<?xml version="1.0" encoding="utf-8" ?><dwsync><file name=".DS_Store" server="educatic.unam.mx//var/www/educatic/htdocs/" local="3536763898" remote="12134058323" /><file name="actualizar.ios9.png" server="educatic.unam.mx//var/www/educatic/htdocs/" local="3531832728" remote="12134058323" /><file name="calificacion.iTunesU.png" server="educatic.unam.mx//var/www/educatic/htdocs/" local="3531832885" remote="12134058323" /><file name="como.activar.las.notificaciones.de.iTunes.pdf" server="educatic.unam.mx//var/www/educatic/htdocs/" local="3531499331" remote="12134058323" /><file name="como.actualizar.ios9.pdf" server="educatic.unam.mx//var/www/educatic/htdocs/" local="3532022566" remote="12134058323" /><file name="como.agregar.mi.nombre.completo.a.mi.apple.pdf" server="educatic.unam.mx//var/www/educatic/htdocs/" local="3531498113" remote="12134058324" /><file name="como.cambiar.el.nombre.a.mi.ipad.pdf" server="educatic.unam.mx//var/www/educatic/htdocs/" local="3531498389" remote="12134058324" /><file name="como.enviar.una.Tarea.en.iTunes.pdf" server="educatic.unam.mx//var/www/educatic/htdocs/" local="3531498845" remote="12134058324" /><file name="como.instalar.la.app.iTunesU.pdf" server="educatic.unam.mx//var/www/educatic/htdocs/" local="3531497790" remote="12134058324" /><file name="como.participar.en.un.debate.en.itunes.pdf" server="educatic.unam.mx//var/www/educatic/htdocs/" local="3531498637" remote="12134058324" /><file name="como.reviso.mi.calificacion.de.una.Tarea.iTunes.pdf" server="educatic.unam.mx//var/www/educatic/htdocs/" local="3531499001" remote="12134058324" /><file name="configura.ios.png" server="educatic.unam.mx//var/www/educatic/htdocs/" local="3531833168" remote="12134058325" /><file name="configurar.ios.despues.de.una.actualizacion.pdf" server="educatic.unam.mx//var/www/educatic/htdocs/" local="3531497444" remote="12134058325" /><file name="debate.itunesU.png" server="educatic.unam.mx//var/www/educatic/htdocs/" local="3531833456" remote="12134058325" /><file name="instalar.itunesU.png" server="educatic.unam.mx//var/www/educatic/htdocs/" local="3531833862" remote="12134058325" /><file name="nombre.id.png" server="educatic.unam.mx//var/www/educatic/htdocs/" local="3531834254" remote="12134058326" /><file name="nombre.ipad.png" server="educatic.unam.mx//var/www/educatic/htdocs/" local="3531834442" remote="12134058327" /><file name="notificaciones.iTunesU.png" server="educatic.unam.mx//var/www/educatic/htdocs/" local="3531834536" remote="12134058327" /><file name="tarea.iTunesu.png" server="educatic.unam.mx//var/www/educatic/htdocs/" local="3531835328" remote="12134058328" /><file name="tabletas.png" server="educatic.unam.mx//var/www/educatic/htdocs/" local="3532622069" remote="12134058328" /><file name="base-numbers.png" server="educatic.unam.mx//var/www/educatic/htdocs/" local="3536249173" remote="12134058323" /><file name="compartir-debate.png" server="educatic.unam.mx//var/www/educatic/htdocs/" local="3536247177" remote="12134058324" /><file name="compartir-numbers.png" server="educatic.unam.mx//var/www/educatic/htdocs/" local="3536248682" remote="12134058325" /><file name="compartir-page.png" server="educatic.unam.mx//var/www/educatic/htdocs/" local="3536249374" remote="12134058325" /><file name="Debate-CompartirLiga.pdf" server="educatic.unam.mx//var/www/educatic/htdocs/" local="3536163802" remote="12134058325" /><file name="edicion-keynote.png" server="educatic.unam.mx//var/www/educatic/htdocs/" local="3536250719" remote="12134058325" /><file name="editar-keynote.png" server="educatic.unam.mx//var/www/educatic/htdocs/" local="3536247723" remote="12134058325" /><file name="funciones-numbers.png" server="educatic.unam.mx//var/www/educatic/htdocs/" local="3536248902" remote="12134058325" /><file name="graficas-numbers.png" server="educatic.unam.mx//var/www/educatic/htdocs/" local="3536249065" remote="12134058325" /><file name="grande-keynote.png" server="educatic.unam.mx//var/www/educatic/htdocs/" local="3536250608" remote="12134058325" /><file name="imagen-pages.png" server="educatic.unam.mx//var/www/educatic/htdocs/" local="3536249492" remote="12134058325" /><file name="Keynote-EditarTexto.pdf" server="educatic.unam.mx//var/www/educatic/htdocs/" local="3536163816" remote="12134058325" /><file name="Keynote-NuevaPresentacion.pdf" server="educatic.unam.mx//var/www/educatic/htdocs/" local="3536163830" remote="12134058325" /><file name="Keynote_editar imagen.pdf" server="educatic.unam.mx//var/www/educatic/htdocs/" local="3536246211" remote="12134058326" /><file name="Numbers-Compartir.pdf" server="educatic.unam.mx//var/www/educatic/htdocs/" local="3536163842" remote="12134058327" /><file name="Numbers-Funciones.pdf" server="educatic.unam.mx//var/www/educatic/htdocs/" local="3536163858" remote="12134058327" /><file name="Numbers-Graficas.pdf" server="educatic.unam.mx//var/www/educatic/htdocs/" local="3536163870" remote="12134058327" /><file name="Numbers-nocionesBasicas.pdf" server="educatic.unam.mx//var/www/educatic/htdocs/" local="3536163882" remote="12134058328" /><file name="Pages-Compartir.pdf" server="educatic.unam.mx//var/www/educatic/htdocs/" local="3536163892" remote="12134058328" /><file name="Pages-Imagenes.pdf" server="educatic.unam.mx//var/www/educatic/htdocs/" local="3536163906" remote="12134058328" /><file name="Pages-ModificarTexto.pdf" server="educatic.unam.mx//var/www/educatic/htdocs/" local="3536163920" remote="12134058328" /><file name="presentacion-keynote.png" server="educatic.unam.mx//var/www/educatic/htdocs/" local="3536248429" remote="12134058328" /><file name="scopeom003.pdf" server="educatic.unam.mx//var/www/educatic/htdocs/" local="3534942591" remote="12134058328" /><file name="texto-pages.png" server="educatic.unam.mx//var/www/educatic/htdocs/" local="3536249656" remote="12134058328" /><file name="keynote-tablas-graficas.pdf" server="educatic.unam.mx//var/www/educatic/htdocs/" local="3536246211" remote="12134058326" /><file name=".DS_Store" server="132.247.146.9//var/www/sitio/htdocs/" local="3536763898" remote="12130412271" /><file name="actualizar.ios9.png" server="132.247.146.9//var/www/sitio/htdocs/" local="3531832728" remote="12130412271" /><file name="base-numbers.png" server="132.247.146.9//var/www/sitio/htdocs/" local="3536249173" remote="12130412271" /><file name="calificacion.iTunesU.png" server="132.247.146.9//var/www/sitio/htdocs/" local="3531832885" remote="12130412271" /><file name="como.activar.las.notificaciones.de.iTunes.pdf" server="132.247.146.9//var/www/sitio/htdocs/" local="3531499331" remote="12130412271" /><file name="como.actualizar.ios9.pdf" server="132.247.146.9//var/www/sitio/htdocs/" local="3532022566" remote="12130412271" /><file name="como.agregar.mi.nombre.completo.a.mi.apple.pdf" server="132.247.146.9//var/www/sitio/htdocs/" local="3531498113" remote="12130412271" /><file name="como.cambiar.el.nombre.a.mi.ipad.pdf" server="132.247.146.9//var/www/sitio/htdocs/" local="3531498389" remote="12130412271" /><file name="como.enviar.una.Tarea.en.iTunes.pdf" server="132.247.146.9//var/www/sitio/htdocs/" local="3531498845" remote="12130412272" /><file name="como.instalar.la.app.iTunesU.pdf" server="132.247.146.9//var/www/sitio/htdocs/" local="3531497790" remote="12130412272" /><file name="como.participar.en.un.debate.en.itunes.pdf" server="132.247.146.9//var/www/sitio/htdocs/" local="3531498637" remote="12130412272" /><file name="como.reviso.mi.calificacion.de.una.Tarea.iTunes.pdf" server="132.247.146.9//var/www/sitio/htdocs/" local="3531499001" remote="12130412272" /><file name="compartir-debate.png" server="132.247.146.9//var/www/sitio/htdocs/" local="3536247177" remote="12130412272" /><file name="compartir-numbers.png" server="132.247.146.9//var/www/sitio/htdocs/" local="3536248682" remote="12130412272" /><file name="compartir-page.png" server="132.247.146.9//var/www/sitio/htdocs/" local="3536249374" remote="12130412272" /><file name="configura.ios.png" server="132.247.146.9//var/www/sitio/htdocs/" local="3531833168" remote="12130412272" /><file name="configurar.ios.despues.de.una.actualizacion.pdf" server="132.247.146.9//var/www/sitio/htdocs/" local="3531497444" remote="12130412272" /><file name="Debate-CompartirLiga.pdf" server="132.247.146.9//var/www/sitio/htdocs/" local="3536163802" remote="12130412272" /><file name="debate.itunesU.png" server="132.247.146.9//var/www/sitio/htdocs/" local="3531833456" remote="12130412272" /><file name="edicion-keynote.png" server="132.247.146.9//var/www/sitio/htdocs/" local="3536250719" remote="12130412272" /><file name="editar-keynote.png" server="132.247.146.9//var/www/sitio/htdocs/" local="3536247723" remote="12130412272" /><file name="funciones-numbers.png" server="132.247.146.9//var/www/sitio/htdocs/" local="3536248902" remote="12130412272" /><file name="graficas-numbers.png" server="132.247.146.9//var/www/sitio/htdocs/" local="3536249065" remote="12130412272" /><file name="grande-keynote.png" server="132.247.146.9//var/www/sitio/htdocs/" local="3536250608" remote="12130412272" /><file name="imagen-pages.png" server="132.247.146.9//var/www/sitio/htdocs/" local="3536249492" remote="12130412272" /><file name="instalar.itunesU.png" server="132.247.146.9//var/www/sitio/htdocs/" local="3531833862" remote="12130412272" /><file name="Keynote-EditarTexto.pdf" server="132.247.146.9//var/www/sitio/htdocs/" local="3536163816" remote="12130412273" /><file name="Keynote-NuevaPresentacion.pdf" server="132.247.146.9//var/www/sitio/htdocs/" local="3536163830" remote="12130412273" /><file name="keynote-tablas-graficas.pdf" server="132.247.146.9//var/www/sitio/htdocs/" local="3536246211" remote="12130412273" /><file name="Keynote_editar imagen.pdf" server="132.247.146.9//var/www/sitio/htdocs/" local="3536246211" remote="12130412273" /><file name="nombre.id.png" server="132.247.146.9//var/www/sitio/htdocs/" local="3531834254" remote="12130412273" /><file name="nombre.ipad.png" server="132.247.146.9//var/www/sitio/htdocs/" local="3531834442" remote="12130412273" /><file name="notificaciones.iTunesU.png" server="132.247.146.9//var/www/sitio/htdocs/" local="3531834536" remote="12130412273" /><file name="Numbers-Compartir.pdf" server="132.247.146.9//var/www/sitio/htdocs/" local="3536163842" remote="12130412273" /><file name="Numbers-Funciones.pdf" server="132.247.146.9//var/www/sitio/htdocs/" local="3536163858" remote="12130412273" /><file name="Numbers-Graficas.pdf" server="132.247.146.9//var/www/sitio/htdocs/" local="3536163870" remote="12130412273" /><file name="Numbers-nocionesBasicas.pdf" server="132.247.146.9//var/www/sitio/htdocs/" local="3536163882" remote="12130412273" /><file name="Pages-Compartir.pdf" server="132.247.146.9//var/www/sitio/htdocs/" local="3536163892" remote="12130412273" /><file name="Pages-Imagenes.pdf" server="132.247.146.9//var/www/sitio/htdocs/" local="3536163906" remote="12130412273" /><file name="Pages-ModificarTexto.pdf" server="132.247.146.9//var/www/sitio/htdocs/" local="3536163920" remote="12130412273" /><file name="presentacion-keynote.png" server="132.247.146.9//var/www/sitio/htdocs/" local="3536248429" remote="12130412273" /><file name="scopeom003.pdf" server="132.247.146.9//var/www/sitio/htdocs/" local="3534942591" remote="12130412274" /><file name="tabletas.png" server="132.247.146.9//var/www/sitio/htdocs/" local="3532622069" remote="12130412274" /><file name="tarea.iTunesu.png" server="132.247.146.9//var/www/sitio/htdocs/" local="3531835328" remote="12130412274" /><file name="texto-pages.png" server="132.247.146.9//var/www/sitio/htdocs/" local="3536249656" remote="12130412274" /></dwsync>