<?xml version="1.0" encoding="utf-8" ?><dwsync><file name="fontawesome-webfont.eot" server="132.247.146.9//var/www/sitio/htdocs/" local="3523884278" remote="12130412265" /><file name="fontawesome-webfont.svg" server="132.247.146.9//var/www/sitio/htdocs/" local="3523884278" remote="12130412265" /><file name="fontawesome-webfont.ttf" server="132.247.146.9//var/www/sitio/htdocs/" local="3523884278" remote="12130412265" /><file name="fontawesome-webfont.woff" server="132.247.146.9//var/www/sitio/htdocs/" local="3523884278" remote="12130412265" /><file name="FontAwesome.otf" server="132.247.146.9//var/www/sitio/htdocs/" local="3523884278" remote="12130412265" /><file name="fontawesome-webfont.eot" server="educatic.unam.mx//var/www/educatic/htdocs/" local="3523884278" remote="12134058317" /><file name="fontawesome-webfont.svg" server="educatic.unam.mx//var/www/educatic/htdocs/" local="3523884278" remote="12134058317" /><file name="fontawesome-webfont.ttf" server="educatic.unam.mx//var/www/educatic/htdocs/" local="3523884278" remote="12134058317" /><file name="fontawesome-webfont.woff" server="educatic.unam.mx//var/www/educatic/htdocs/" local="3523884278" remote="12134058317" /><file name="FontAwesome.otf" server="educatic.unam.mx//var/www/educatic/htdocs/" local="3523884278" remote="12134058318" /><file name="fontawesome-webfont.eot" server="www.educatic.unam.mx//var/www/educatic/htdocs/" local="3523884278" remote="12117645823" /><file name="fontawesome-webfont.svg" server="www.educatic.unam.mx//var/www/educatic/htdocs/" local="3523884278" remote="12117645823" /><file name="fontawesome-webfont.ttf" server="www.educatic.unam.mx//var/www/educatic/htdocs/" local="3523884278" remote="12117645823" /><file name="fontawesome-webfont.woff" server="www.educatic.unam.mx//var/www/educatic/htdocs/" local="3523884278" remote="12117645823" /><file name="FontAwesome.otf" server="www.educatic.unam.mx//var/www/educatic/htdocs/" local="3523884278" remote="12117645823" /></dwsync>